{
  "region": "kr",
  "namespace": "profile-classicann-kr",
  "locale": "ko_KR",
  "updated_at": "2026-03-03T12:54:33.950069+00:00",
  "total_characters_scanned": 3013,
  "total_with_pvp": 760,
  "guilds_scanned": [
    "Balance",
    "Unreal",
    "불타는성전",
    "ovo",
    "동행",
    "arena",
    "부산",
    "suntory",
    "낄낄",
    "계속해보겠습니다"
  ],
  "brackets": {
    "2v2": {
      "count": 325,
      "file": "2v2.json"
    },
    "3v3": {
      "count": 117,
      "file": "3v3.json"
    },
    "5v5": {
      "count": 612,
      "file": "5v5.json"
    }
  }
}